{
  "": {
    "bitis_tarihi": "2027-02-16",
    "video_hakki": 410,
    "baslangic_sayaci": 0,
    "paket_ismi": "YILLIK ALTIN"
  },
  "ADMIN_BURAYA_HWID": {
    "bitis_tarihi": "2030-01-01",
    "video_hakki": 9999,
    "baslangic_sayaci": 0,
    "paket_ismi": "ADMIN PRO"
  },
  "GUMUS_HWID_BURAYA": {
    "bitis_tarihi": "2025-08-14",
    "video_hakki": 50,
    "baslangic_sayaci": 0,
    "paket_ismi": "3 AYLIK GÜMÜŞ"
  },
  "PLATIN_HWID_BURAYA": {
    "bitis_tarihi": "2025-11-14",
    "video_hakki": 150,
    "baslangic_sayaci": 0,
    "paket_ismi": "6 AYLIK PLATİN"
  },
  "N0CY1734MB0013069": {
    "bitis_tarihi": "2026-05-31",
    "video_hakki": 5,
    "baslangic_sayaci": 0,
    "paket_ismi": "DENEME"
  }
}
